astro_toolbox/__init__.py
astro_toolbox/__main__.py
astro_toolbox/command_line.py
astro_toolbox/angle/__init__.py
astro_toolbox/angle/degrees.py
astro_toolbox/angle/dms.py
astro_toolbox/angle/hms.py
astro_toolbox/angle/radians.py
astro_toolbox/coordinates/__init__.py
astro_toolbox/coordinates/equatorial.py
astro_toolbox/coordinates/horizontal.py
astro_toolbox/coordinates/location.py
astro_toolbox/coordinates/solar_system.py
astro_toolbox/coordinates/data/orbital_elements.json
astro_toolbox/query/__init__.py
astro_toolbox/query/catalogs.py
astro_toolbox/query/ephemeris.py
astro_toolbox/query/weather.py
astro_toolbox/query/weather_icons/cloudy.png
astro_toolbox/query/weather_icons/direction_down.png
astro_toolbox/query/weather_icons/direction_down_left.png
astro_toolbox/query/weather_icons/direction_down_right.png
astro_toolbox/query/weather_icons/direction_left.png
astro_toolbox/query/weather_icons/direction_right.png
astro_toolbox/query/weather_icons/direction_up.png
astro_toolbox/query/weather_icons/direction_up_left.png
astro_toolbox/query/weather_icons/direction_up_right.png
astro_toolbox/query/weather_icons/drizzle.png
astro_toolbox/query/weather_icons/fog.png
astro_toolbox/query/weather_icons/mainly_clear.png
astro_toolbox/query/weather_icons/na.png
astro_toolbox/query/weather_icons/partly_cloudy.png
astro_toolbox/query/weather_icons/rain.png
astro_toolbox/query/weather_icons/showers.png
astro_toolbox/query/weather_icons/snow.png
astro_toolbox/query/weather_icons/sunny.png
astro_toolbox/query/weather_icons/thunderstorm.png
astro_toolbox/scripts/__init__.py
astro_toolbox/scripts/planning.py
astro_toolbox/scripts/plots.py
astro_toolbox/time/__init__.py
astro_toolbox/time/core.py
astro_toolbox/utils/python_functions.py
astro_toolbox/utils/strparser.py
astro_toolbox-0.1.3.dist-info/LICENSE
astro_toolbox-0.1.3.dist-info/METADATA
astro_toolbox-0.1.3.dist-info/WHEEL
astro_toolbox-0.1.3.dist-info/entry_points.txt
astro_toolbox-0.1.3.dist-info/top_level.txt
astro_toolbox-0.1.3.dist-info/RECORD
