Metadata-Version: 2.1
Name: astro-toolbox
Version: 0.1.3
Summary: Toolbox for observationnal astronomy.
Author-email: Romain Loustalet Palengat <romain.loustalet@gmx.com>
Project-URL: Homepage, https://github.com/rloustalet/astro_toolbox
Project-URL: Source, https://github.com/rloustalet/astro_toolbox
Project-URL: Documentation, https://astro-toolbox.readthedocs.io/en/latest/
Keywords: astro,toolbox,astro_toolbox,observationnal
Platform: unix
Platform: linux
Platform: osx
Platform: cygwin
Platform: win32
Classifier: License :: OSI Approved :: GNU General Public License (GPL)
Classifier: Programming Language :: Python :: 3.10
Classifier: Programming Language :: Python :: 3.11
Classifier: Topic :: Software Development :: Libraries
Requires-Python: >=3.10
License-File: LICENSE
Requires-Dist: numpy (>=1.20)
Requires-Dist: rich (>=12.6.0)
Requires-Dist: xmltodict (>=0.13.0)
Requires-Dist: click (>=8.1.3)
Requires-Dist: matplotlib (>=3.5.0)
Requires-Dist: Pillow (>=9.3.0)
Provides-Extra: doc
Requires-Dist: sphinx ; extra == 'doc'
Requires-Dist: sphinx-rtd-theme ; extra == 'doc'
Requires-Dist: sphinx-autodocgen ; extra == 'doc'
Requires-Dist: Sphinx (>=3.0.0) ; extra == 'doc'
Provides-Extra: test
Requires-Dist: pytest ; extra == 'test'
